mlops_crispdm/__init__.py
mlops_crispdm/business.py
mlops_crispdm/cli.py
mlops_crispdm/data_preparation.py
mlops_crispdm/data_understanding.py
mlops_crispdm/deployment.py
mlops_crispdm/evaluation.py
mlops_crispdm/modeling.py
mlops_crispdm_ci_cd-0.0.4.dist-info/METADATA
mlops_crispdm_ci_cd-0.0.4.dist-info/WHEEL
mlops_crispdm_ci_cd-0.0.4.dist-info/entry_points.txt
mlops_crispdm_ci_cd-0.0.4.dist-info/top_level.txt
mlops_crispdm_ci_cd-0.0.4.dist-info/RECORD
