Metadata-Version: 2.4
Name: mlops-crispdm-ci-cd
Version: 0.0.4
Summary: Proyecto demo MLOps siguiendo CRISP-DM
Requires-Python: >=3.9
